graphpy/BFSstrategy.py
graphpy/DFSstrategy.py
graphpy/__init__.py
graphpy/edge.py
graphpy/graph.py
graphpy/graph_utils.py
graphpy/search_strategy.py
graphpy/vertex.py
graphpython-0.83.dist-info/METADATA
graphpython-0.83.dist-info/RECORD
graphpython-0.83.dist-info/WHEEL
graphpython-0.83.dist-info/top_level.txt
