Metadata-Version: 2.1
Name: graphpython
Version: 0.83
Summary: package to manipulate graphs
Home-page: https://github.com/igornfaustino/graphpy
Author: Claudia Lazara Poiet Sampedro, Igor Neves Faustino, Leticia Mazzo Portela
Author-email: clp.sampedro@gmail.com, igornfaustino@gmail.com, leticiaportela@alunos.utfpr.edu.br
License: MIT
Platform: UNKNOWN
Requires-Dist: six
